robobase/__init__.py
robobase/object.py
robobase/system.py
robo_base-0.1.5.dist-info/LICENSE
robo_base-0.1.5.dist-info/METADATA
robo_base-0.1.5.dist-info/WHEEL
robo_base-0.1.5.dist-info/top_level.txt
robo_base-0.1.5.dist-info/RECORD
