Metadata-Version: 2.1
Name: robo-base
Version: 0.1.5
Summary: base modules, objects, classes
Home-page: https://github.com/mkner/robo-base
Author: Mike Knerr
License: BSD
Keywords: python,packages
Platform: UNKNOWN
Classifier: Programming Language :: Python :: 3
Classifier: License :: OSI Approved :: BSD License
Classifier: Operating System :: OS Independent
License-File: LICENSE
